{"changelog.md":"VYZQ8hwS","en_index.md":"DSuZ6F_I","en_zh_options.md":"DNPmwXr0","en_zh_use-drag.md":"DcdoKafx","en_zh_use-gesture.md":"DEyr-KLq","en_zh_use-hover.md":"DIp_ma02","en_zh_use-move.md":"DWcbHKBW","en_zh_use-pinch.md":"DxkgtYVP","en_zh_use-scroll.md":"BCiE7_Yu","en_zh_use-spring.md":"CavicENi","en_zh_use-wheel.md":"Clz-N8NX","index.md":"C2b7vvUJ","readme.md":"DaX3ZYcx","zh_options.md":"kKiJEMz5","zh_use-drag.md":"r6gc4-Pe","zh_use-gesture.md":"Dr89XMuo","zh_use-hover.md":"Z5GgFYdc","zh_use-move.md":"D5OFz2us","zh_use-pinch.md":"CpoOBlob","zh_use-scroll.md":"DRf-Fl-z","zh_use-spring.md":"KHqLaDdP","zh_use-wheel.md":"CpSMQtVj"}
